coveralls/__init__.py
coveralls/__main__.py
coveralls/api.py
coveralls/cli.py
coveralls/exception.py
coveralls/git.py
coveralls/reporter.py
coveralls-4.0.0.dist-info/LICENSE.rst
coveralls-4.0.0.dist-info/METADATA
coveralls-4.0.0.dist-info/WHEEL
coveralls-4.0.0.dist-info/entry_points.txt
coveralls-4.0.0.dist-info/RECORD
