Metadata-Version: 2.1
Name: coveralls
Version: 4.0.0
Summary: Show coverage stats online via coveralls.io
Home-page: http://github.com/TheKevJames/coveralls-python
License: MIT
Author: Kevin James
Author-email: coveralls-python@thekev.in
Requires-Python: >=3.8,<3.13
Classifier: Development Status :: 5 - Production/Stable
Classifier: Intended Audience :: Developers
Classifier: License :: OSI Approved :: MIT License
Classifier: Operating System :: OS Independent
Classifier: Programming Language :: Python :: 3
Classifier: Programming Language :: Python :: 3.8
Classifier: Programming Language :: Python :: 3.9
Classifier: Programming Language :: Python :: 3.10
Classifier: Programming Language :: Python :: 3.11
Classifier: Programming Language :: Python :: 3.12
Classifier: Programming Language :: Python :: Implementation :: CPython
Classifier: Programming Language :: Python :: Implementation :: PyPy
Classifier: Topic :: Software Development :: Testing
Provides-Extra: yaml
Requires-Dist: coverage[toml] (>=5.0,<7.5,!=6.0.*,!=6.1,!=6.1.1)
Requires-Dist: docopt (>=0.6.1,<0.7.0)
Requires-Dist: pyyaml (>=3.10,<7.0) ; extra == "yaml"
Requires-Dist: requests (>=1.0.0,<3.0.0)
Project-URL: Changelog, https://github.com/TheKevJames/coveralls-python/blob/master/CHANGELOG.md
Project-URL: Docs, https://coveralls-python.rtfd.io/
Project-URL: Repository, http://github.com/TheKevJames/coveralls-python
